ch.py
filestore/__init__.py
filestore/exceptions.py
filestore/localstorage.py
filestore/main.py
filestore/memorystorage.py
filestore/s3.py
filestore/store.py
filestore/structs.py
filestore/util.py
filestore/storage_engines/__init__.py
filestore/storage_engines/local_engine.py
filestore/storage_engines/memory_engine.py
filestore/storage_engines/s3_engine.py
filestore/storage_engines/storage_engine.py
filestore-1.0.8.dist-info/LICENSE
filestore-1.0.8.dist-info/METADATA
filestore-1.0.8.dist-info/WHEEL
filestore-1.0.8.dist-info/top_level.txt
filestore-1.0.8.dist-info/RECORD
