Metadata-Version: 2.1
Name: filestore
Version: 1.0.8
Summary: Storage Engine Package for FastAPI
Author-email: Ichinga Samuel <ichingasamuel@gmail.com>
Project-URL: Homepage, https://github.com/Ichinga-Samuel/faststore
Project-URL: Bug Tracker, https://github.com/Ichinga-Samuel/faststore/issues
Keywords: fastapi,filestorage,cloudstorage,storageengine,filestore
Classifier: Programming Language :: Python :: 3
Classifier: License :: OSI Approved :: MIT License
Classifier: Operating System :: OS Independent
Requires-Python: >=3.8
License-File: LICENSE
Requires-Dist: fastapi
Requires-Dist: python-multipart
Provides-Extra: s3
Requires-Dist: boto3 ; extra == 's3'
